django_admin_plugin/__init__.py
django_admin_plugin/admin.py
django_admin_plugin/apps.py
django_admin_plugin/settings.py
django_admin_plugin/management/__init__.py
django_admin_plugin/management/commands/__init__.py
django_admin_plugin/management/commands/init_admin_plugin.py
django_admin_plugin-0.1.5.dist-info/LICENSE.md
django_admin_plugin-0.1.5.dist-info/METADATA
django_admin_plugin-0.1.5.dist-info/WHEEL
django_admin_plugin-0.1.5.dist-info/top_level.txt
django_admin_plugin-0.1.5.dist-info/RECORD
