Metadata-Version: 2.1
Name: django-admin-plugin
Version: 0.1.5
Summary: Useful plugins to enhance django admin
Home-page: https://github.com/amin-basiri/django-admin-plugin
Author: Amin Basiri
Author-email: amin.bsr99@gmail.com
License: BSD-3-Clause
Classifier: Environment :: Web Environment
Classifier: Framework :: Django
Classifier: Framework :: Django :: 3.2
Classifier: Framework :: Django :: 4.2
Classifier: License :: OSI Approved :: BSD License
Classifier: Operating System :: OS Independent
Classifier: Programming Language :: Python
Classifier: Programming Language :: Python :: 3.9
Requires-Python: >=3.9
License-File: LICENSE.md
Requires-Dist: Django >=3.2
